src/__init__.py
src/cli.py
src/config.py
src/data_ingestor.py
scooters_data_uploader-1.2.1.dist-info/METADATA
scooters_data_uploader-1.2.1.dist-info/WHEEL
scooters_data_uploader-1.2.1.dist-info/entry_points.txt
scooters_data_uploader-1.2.1.dist-info/top_level.txt
scooters_data_uploader-1.2.1.dist-info/RECORD
