Metadata-Version: 2.4
Name: scooters-data-uploader
Version: 1.2.1
Summary: Upload educational sample data to PostgreSQL database
Author-email: "Inzhenerka.Tech" <info@inzhenerka.tech>
Project-URL: Homepage, https://github.com/Inzhenerka/scooters_data_uploader
Project-URL: Repository, https://github.com/Inzhenerka/scooters_data_uploader
Project-URL: Issues, https://github.com/Inzhenerka/scooters_data_uploader/issues
Project-URL: Changelog, https://github.com/Inzhenerka/scooters_data_uploader/blob/main/CHANGELOG.md
Keywords: uploader,scooters,data,duckdb,postgresql
Classifier: Programming Language :: Python :: 3
Classifier: Operating System :: OS Independent
Requires-Python: >=3.9
Requires-Dist: duckdb==1.4.0
Requires-Dist: typer==0.19.2
Requires-Dist: rich==14.1.0
